django_tos_uploader-1.1.1.dist-info/licenses/LICENSE
tos_uploader/__init__.py
tos_uploader/apps.py
tos_uploader/fields.py
tos_uploader/widgets.py
tos_uploader/static/tos_uploader/css/uploader.css
tos_uploader/static/tos_uploader/js/uploader.js
tos_uploader/templates/tos_uploader/widget.html
django_tos_uploader-1.1.1.dist-info/METADATA
django_tos_uploader-1.1.1.dist-info/WHEEL
django_tos_uploader-1.1.1.dist-info/top_level.txt
django_tos_uploader-1.1.1.dist-info/RECORD
