Metadata-Version: 2.4
Name: django-tos-uploader
Version: 1.1.1
Summary: Django widget for uploading files to Volcengine TOS (Tinder Object Storage)
Home-page: https://github.com/ren000thomas/django-tos-uploader
Author: Your Name
Author-email: Ren Thomas <ren000thomas@gmail.com>
License: MIT
Project-URL: Homepage, https://github.com/ren000thomas/django-tos-uploader
Project-URL: Bug Reports, https://github.com/ren000thomas/django-tos-uploader/issues
Project-URL: Source, https://github.com/ren000thomas/django-tos-uploader
Project-URL: Documentation, https://github.com/ren000thomas/django-tos-uploader#readme
Keywords: django,volcengine,tos,upload,widget,file-upload
Classifier: Development Status :: 4 - Beta
Classifier: Intended Audience :: Developers
Classifier: License :: OSI Approved :: MIT License
Classifier: Operating System :: OS Independent
Classifier: Programming Language :: Python :: 3
Classifier: Programming Language :: Python :: 3.8
Classifier: Programming Language :: Python :: 3.9
Classifier: Programming Language :: Python :: 3.10
Classifier: Programming Language :: Python :: 3.11
Classifier: Framework :: Django
Classifier: Framework :: Django :: 3.2
Classifier: Framework :: Django :: 4.0
Classifier: Framework :: Django :: 4.1
Classifier: Framework :: Django :: 4.2
Classifier: Framework :: Django :: 5.0
Classifier: Framework :: Django :: 5.1
Classifier: Framework :: Django :: 5.2
Classifier: Topic :: Internet :: WWW/HTTP
Classifier: Topic :: Software Development :: Libraries :: Python Modules
Requires-Python: >=3.8
License-File: LICENSE
Requires-Dist: Django>=3.2
Requires-Dist: volcengine>=1.0.0
Dynamic: author
Dynamic: home-page
Dynamic: license-file
Dynamic: requires-python
